ztest.py
ztest-0.0.1.dist-info/METADATA
ztest-0.0.1.dist-info/WHEEL
ztest-0.0.1.dist-info/top_level.txt
ztest-0.0.1.dist-info/RECORD
