Metadata-Version: 2.1
Name: ztest
Version: 0.0.1
Summary: Zelos Cloud Test Python API
Author-email: Zelos Cloud Test <info@zeloscloud.io>
Classifier: Programming Language :: Python :: 3
Classifier: License :: Other/Proprietary License
Classifier: Operating System :: OS Independent
Requires-Python: >=3.7
